clspack/__init__.py
clspack/utils.py
clspack-0.0.2.dist-info/LICENSE
clspack-0.0.2.dist-info/METADATA
clspack-0.0.2.dist-info/WHEEL
clspack-0.0.2.dist-info/top_level.txt
clspack-0.0.2.dist-info/RECORD
