Metadata-Version: 2.1
Name: clspack
Version: 0.0.2
Summary: clspack is a python library that packagizes python classes
Home-page: https://github.com/not-lain/clspack
Author-email: hhichri60@gmail.com
License: Apache 2.0 License
Classifier: Topic :: Utilities
Classifier: Programming Language :: Python :: 3.9
Requires: setuptools
Requires: wheel
License-File: LICENSE
